autdec/__init__.py
autdec/bb_cln.py
autdec/code_capacity.py
autdec/dem_utils.py
autdec/igraph_auts.py
autdec/perm_utils.py
autdec/py.typed
autdec-0.1.1.dist-info/LICENSE
autdec-0.1.1.dist-info/METADATA
autdec-0.1.1.dist-info/WHEEL
autdec-0.1.1.dist-info/RECORD
