Metadata-Version: 2.3
Name: autdec
Version: 0.1.1
Summary: Automorphism Ensemble Decoder for Quantum Stabilizer Codes
License: MIT
Keywords: quantum computing,quantum error correction,quantum low-density parity check codes,decoding,LDPC
Author: Hasan Sayginel
Author-email: hasan.sayginel.17@ucl.ac.uk
Requires-Python: >=3.11
Classifier: Intended Audience :: Science/Research
Classifier: License :: OSI Approved :: MIT License
Classifier: Natural Language :: English
Classifier: Operating System :: OS Independent
Classifier: Programming Language :: Python :: 3
Classifier: Programming Language :: Python :: 3.11
Classifier: Programming Language :: Python :: 3.12
Classifier: Programming Language :: Python :: 3.13
Classifier: Topic :: Scientific/Engineering :: Mathematics
Classifier: Topic :: Scientific/Engineering :: Physics
Requires-Dist: igraph (>=0.11.8)
Requires-Dist: ldpc (==2.1.2)
Requires-Dist: matplotlib (>=3.10.1)
Requires-Dist: numba (>=0.61.0)
Requires-Dist: numpy (>=2.1.3)
Requires-Dist: scipy (>=1.15.2)
Requires-Dist: statsmodels (>=0.14.4)
Requires-Dist: stim (>=1.14.0)
Requires-Dist: sympy (>=1.13.3)
Project-URL: Repository, https://github.com/hsayginel/autdec
